dicencards/__init__.py
dicencards/cards.py
dicencards/dice.py
dicencards-0.1.1.dist-info/LICENSE.txt
dicencards-0.1.1.dist-info/METADATA
dicencards-0.1.1.dist-info/WHEEL
dicencards-0.1.1.dist-info/top_level.txt
dicencards-0.1.1.dist-info/RECORD
